<ValueSet xmlns="http://hl7.org/fhir"> 
	<id value="manifestation-or-symptom-vs"/>
 <url value="http://ValueSet.hl7fhir.cn/manifestation-or-symptom-vs"/>
 <name value="manifestation-or-symptom-vs"/><!-- ?? 0..1 Name for this value set (computer friendly) -->
 <title value="编码症状"/><!-- 0..1 Name for this value set (human friendly) -->
 <status value="draft"/><!-- 1..1 draft | active | retired | unknown -->
 <compose>  <!-- 0..1 Content logical definition of the value set (CLD) --> 
  <include>  <!-- 1..* Include one or more codes from a code system or other value set(s) -->
   <system value="http://snomed.info/sct"/><!-- ?? 0..1 The system the codes come from --> 
  </include>
  <exclude><!-- ?? 0..* Content as for ValueSet.compose.include Explicitly exclude codes from a code system or other value sets --></exclude>
 </compose>
</ValueSet>
